{"cursos":["2025\/2026","2024\/2025","2023\/2024","2022\/2023"],"provincias":{"4":"Almer\u00eda","11":"C\u00e1diz","14":"C\u00f3rdoba","18":"Granada","21":"Huelva","23":"Ja\u00e9n","29":"M\u00e1laga","41":"Sevilla"},"posiciones":{"2100":{"2022\/2023":[{"f":"09\/09\/22","t":"S","p":"11"}]},"2322":{"2022\/2023":[{"f":"13\/09\/22","t":"S","p":"21"}]},"2562":{"2022\/2023":[{"f":"13\/09\/22","t":"S","p":"11"}]},"2655":{"2022\/2023":[{"f":"22\/09\/22","t":"S","p":"4"}]},"2656":{"2022\/2023":[{"f":"22\/09\/22","t":"S","p":"4"}]},"2865":{"2022\/2023":[{"f":"15\/11\/22","t":"S","p":"4"}]},"2869":{"2022\/2023":[{"f":"06\/10\/22","t":"S","p":"4"}]},"2884":{"2022\/2023":[{"f":"10\/01\/23","t":"V","p":"4"}]},"2929":{"2022\/2023":[{"f":"22\/09\/22","t":"S","p":"4"}]},"3041":{"2022\/2023":[{"f":"22\/09\/22","t":"V","p":"4"}]},"3132":{"2022\/2023":[{"f":"22\/09\/22","t":"V","p":"4"}]},"3320":{"2022\/2023":[{"f":"29\/11\/22","t":"S","p":"23"}]},"3817":{"2023\/2024":[{"f":"05\/09\/23","t":"S","p":"4"}]},"3908":{"2023\/2024":[{"f":"11\/09\/23","t":"V","p":"4"}]},"3951":{"2023\/2024":[{"f":"11\/09\/23","t":"V","p":"4"}]},"4019":{"2023\/2024":[{"f":"11\/09\/23","t":"V","p":"4"}]},"4209":{"2023\/2024":[{"f":"19\/09\/23","t":"S","p":"4"}]},"4809":{"2023\/2024":[{"f":"21\/09\/23","t":"S","p":"18"}]},"4843":{"2023\/2024":[{"f":"09\/11\/23","t":"S","p":"4"}]},"4977":{"2023\/2024":[{"f":"17\/10\/23","t":"S","p":"4"}]},"5114":{"2022\/2023":[{"f":"16\/02\/23","t":"S","p":"4"}]},"5157":{"2022\/2023":[{"f":"07\/03\/23","t":"S","p":"4"}]},"5217":{"2023\/2024":[{"f":"16\/01\/24","t":"S","p":"4"}]},"5272":{"2023\/2024":[{"f":"25\/01\/24","t":"S","p":"18"}]},"5336":{"2022\/2023":[{"f":"18\/04\/23","t":"S","p":"11"}]},"5381":{"2022\/2023":[{"f":"11\/05\/23","t":"S","p":"4"}]},"5404":{"2022\/2023":[{"f":"18\/05\/23","t":"S","p":"4"}]},"5425":{"2023\/2024":[{"f":"07\/03\/24","t":"S","p":"4"}]},"5500":{"2023\/2024":[{"f":"20\/03\/24","t":"S","p":"4"}]},"5506":{"2023\/2024":[{"f":"13\/02\/24","t":"S","p":"4"}]},"5654":{"2023\/2024":[{"f":"23\/04\/24","t":"S","p":"4"}]},"5764":{"2023\/2024":[{"f":"16\/05\/24","t":"S","p":"4"}]},"5864":{"2023\/2024":[{"f":"04\/06\/24","t":"S","p":"4"}]}}}