{"cursos":["2025\/2026","2024\/2025","2023\/2024","2022\/2023"],"provincias":{"4":"Almer\u00eda","11":"C\u00e1diz","14":"C\u00f3rdoba","18":"Granada","21":"Huelva","23":"Ja\u00e9n","29":"M\u00e1laga","41":"Sevilla"},"posiciones":{"30":{"2022\/2023":[{"f":"05\/09\/22","t":"V","p":"29"}]},"34":{"2022\/2023":[{"f":"05\/09\/22","t":"V","p":"14"}]},"35":{"2022\/2023":[{"f":"05\/09\/22","t":"V","p":"29"}]},"46":{"2022\/2023":[{"f":"05\/09\/22","t":"V","p":"29"}]},"80":{"2022\/2023":[{"f":"05\/09\/22","t":"V","p":"29"}]},"83":{"2022\/2023":[{"f":"05\/09\/22","t":"V","p":"14"}]},"91":{"2022\/2023":[{"f":"05\/09\/22","t":"V","p":"29"}]},"104":{"2022\/2023":[{"f":"05\/09\/22","t":"V","p":"29"}]},"129":{"2022\/2023":[{"f":"05\/09\/22","t":"V","p":"18"}]},"140":{"2022\/2023":[{"f":"05\/09\/22","t":"V","p":"29"}]},"215":{"2022\/2023":[{"f":"05\/09\/22","t":"V","p":"29"}]},"220":{"2022\/2023":[{"f":"05\/09\/22","t":"V","p":"18"}]},"229":{"2022\/2023":[{"f":"05\/09\/22","t":"V","p":"29"}]},"245":{"2022\/2023":[{"f":"05\/09\/22","t":"V","p":"14"}]},"256":{"2022\/2023":[{"f":"05\/09\/22","t":"V","p":"14"}]},"261":{"2022\/2023":[{"f":"05\/09\/22","t":"V","p":"29"}]},"264":{"2022\/2023":[{"f":"05\/09\/22","t":"V","p":"29"}]},"306":{"2022\/2023":[{"f":"05\/09\/22","t":"V","p":"29"}]},"310":{"2022\/2023":[{"f":"05\/09\/22","t":"V","p":"41"}]},"323":{"2022\/2023":[{"f":"05\/09\/22","t":"V","p":"29"}]},"332":{"2022\/2023":[{"f":"05\/09\/22","t":"V","p":"29"}]},"339":{"2022\/2023":[{"f":"05\/09\/22","t":"V","p":"29"}]},"358":{"2022\/2023":[{"f":"05\/09\/22","t":"V","p":"29"}]},"362":{"2022\/2023":[{"f":"05\/09\/22","t":"V","p":"23"}]},"369":{"2022\/2023":[{"f":"05\/09\/22","t":"V","p":"29"}]},"371":{"2022\/2023":[{"f":"05\/09\/22","t":"V","p":"29"}]},"377":{"2022\/2023":[{"f":"05\/09\/22","t":"V","p":"14"}]},"379":{"2022\/2023":[{"f":"05\/09\/22","t":"V","p":"29"}]},"380":{"2022\/2023":[{"f":"05\/09\/22","t":"V","p":"29"}]},"397":{"2022\/2023":[{"f":"05\/09\/22","t":"V","p":"4"}]},"402":{"2022\/2023":[{"f":"05\/09\/22","t":"V","p":"29"}]},"406":{"2022\/2023":[{"f":"05\/09\/22","t":"V","p":"29"}]},"416":{"2022\/2023":[{"f":"05\/09\/22","t":"V","p":"11"}]},"420":{"2022\/2023":[{"f":"05\/09\/22","t":"V","p":"14"}]},"432":{"2022\/2023":[{"f":"05\/09\/22","t":"V","p":"18"}]},"433":{"2022\/2023":[{"f":"05\/09\/22","t":"V","p":"41"}]},"446":{"2022\/2023":[{"f":"05\/09\/22","t":"V","p":"29"}]},"452":{"2022\/2023":[{"f":"05\/09\/22","t":"V","p":"29"}]},"455":{"2022\/2023":[{"f":"05\/09\/22","t":"V","p":"29"}]},"456":{"2022\/2023":[{"f":"05\/09\/22","t":"V","p":"23"}]},"463":{"2022\/2023":[{"f":"05\/09\/22","t":"V","p":"18"}]},"471":{"2022\/2023":[{"f":"05\/09\/22","t":"V","p":"23"}]},"474":{"2022\/2023":[{"f":"05\/09\/22","t":"V","p":"29"}]},"477":{"2022\/2023":[{"f":"05\/09\/22","t":"V","p":"11"}]},"489":{"2022\/2023":[{"f":"05\/09\/22","t":"V","p":"29"}]},"494":{"2022\/2023":[{"f":"05\/09\/22","t":"V","p":"14"}]},"515":{"2022\/2023":[{"f":"27\/09\/22","t":"S","p":"23"}]},"521":{"2022\/2023":[{"f":"05\/09\/22","t":"V","p":"29"}]},"525":{"2022\/2023":[{"f":"05\/09\/22","t":"V","p":"29"}]},"532":{"2022\/2023":[{"f":"05\/09\/22","t":"V","p":"29"}]},"545":{"2022\/2023":[{"f":"30\/05\/23","t":"S","p":"29"}]},"547":{"2022\/2023":[{"f":"05\/09\/22","t":"V","p":"21"}]},"555":{"2022\/2023":[{"f":"05\/09\/22","t":"V","p":"41"}]},"559":{"2022\/2023":[{"f":"05\/09\/22","t":"V","p":"41"}]},"560":{"2022\/2023":[{"f":"05\/09\/22","t":"V","p":"29"}]},"562":{"2022\/2023":[{"f":"05\/09\/22","t":"V","p":"11"}]},"565":{"2022\/2023":[{"f":"05\/09\/22","t":"V","p":"29"}]},"566":{"2022\/2023":[{"f":"05\/09\/22","t":"V","p":"11"}]},"569":{"2022\/2023":[{"f":"05\/09\/22","t":"V","p":"21"}]},"570":{"2022\/2023":[{"f":"05\/09\/22","t":"V","p":"11"}]},"583":{"2022\/2023":[{"f":"05\/09\/22","t":"V","p":"41"}]},"587":{"2022\/2023":[{"f":"05\/09\/22","t":"V","p":"21"}]},"590":{"2022\/2023":[{"f":"05\/09\/22","t":"V","p":"29"}]},"592":{"2022\/2023":[{"f":"05\/09\/22","t":"V","p":"41"}]},"604":{"2022\/2023":[{"f":"05\/09\/22","t":"V","p":"41"}]},"606":{"2022\/2023":[{"f":"05\/09\/22","t":"V","p":"41"}]},"608":{"2022\/2023":[{"f":"05\/09\/22","t":"V","p":"14"}]},"612":{"2022\/2023":[{"f":"05\/09\/22","t":"V","p":"41"}]},"614":{"2022\/2023":[{"f":"05\/09\/22","t":"V","p":"11"}]},"616":{"2022\/2023":[{"f":"05\/09\/22","t":"V","p":"29"}]},"619":{"2022\/2023":[{"f":"05\/09\/22","t":"V","p":"41"}]},"620":{"2022\/2023":[{"f":"05\/09\/22","t":"V","p":"29"}]},"622":{"2022\/2023":[{"f":"05\/09\/22","t":"V","p":"29"}]},"626":{"2022\/2023":[{"f":"05\/09\/22","t":"V","p":"41"}]},"632":{"2022\/2023":[{"f":"05\/09\/22","t":"V","p":"11"}]},"633":{"2022\/2023":[{"f":"05\/09\/22","t":"V","p":"41"}]},"635":{"2022\/2023":[{"f":"05\/09\/22","t":"V","p":"29"}]},"646":{"2022\/2023":[{"f":"05\/09\/22","t":"V","p":"29"}]},"648":{"2022\/2023":[{"f":"05\/09\/22","t":"V","p":"29"}]},"655":{"2022\/2023":[{"f":"05\/09\/22","t":"V","p":"41"}]},"656":{"2022\/2023":[{"f":"05\/09\/22","t":"V","p":"41"}]},"681":{"2022\/2023":[{"f":"05\/09\/22","t":"V","p":"41"}]},"685":{"2022\/2023":[{"f":"05\/09\/22","t":"V","p":"14"}]},"687":{"2022\/2023":[{"f":"05\/09\/22","t":"V","p":"11"}]},"692":{"2022\/2023":[{"f":"05\/09\/22","t":"V","p":"11"}]},"698":{"2022\/2023":[{"f":"05\/09\/22","t":"V","p":"21"}]},"704":{"2022\/2023":[{"f":"25\/10\/22","t":"S","p":"29"}]},"705":{"2022\/2023":[{"f":"05\/09\/22","t":"V","p":"11"}]},"725":{"2022\/2023":[{"f":"05\/09\/22","t":"V","p":"11"}]},"728":{"2022\/2023":[{"f":"05\/09\/22","t":"V","p":"41"}]},"759":{"2022\/2023":[{"f":"05\/09\/22","t":"V","p":"41"}]},"772":{"2022\/2023":[{"f":"05\/09\/22","t":"V","p":"4"}]},"773":{"2022\/2023":[{"f":"05\/09\/22","t":"V","p":"11"}]},"779":{"2022\/2023":[{"f":"05\/09\/22","t":"V","p":"41"}]},"784":{"2022\/2023":[{"f":"05\/09\/22","t":"V","p":"41"}]},"788":{"2022\/2023":[{"f":"05\/09\/22","t":"V","p":"11"}]},"790":{"2022\/2023":[{"f":"05\/09\/22","t":"V","p":"11"}]},"796":{"2022\/2023":[{"f":"05\/09\/22","t":"V","p":"4"}]},"804":{"2022\/2023":[{"f":"05\/09\/22","t":"V","p":"41"}]},"805":{"2022\/2023":[{"f":"05\/09\/22","t":"V","p":"41"}]},"806":{"2022\/2023":[{"f":"05\/09\/22","t":"V","p":"4"}]},"807":{"2022\/2023":[{"f":"02\/02\/23","t":"S","p":"29"}]},"816":{"2022\/2023":[{"f":"05\/09\/22","t":"V","p":"41"}]},"818":{"2022\/2023":[{"f":"05\/09\/22","t":"V","p":"41"}]},"824":{"2022\/2023":[{"f":"05\/09\/22","t":"V","p":"4"}]},"826":{"2022\/2023":[{"f":"05\/09\/22","t":"V","p":"41"}]},"827":{"2022\/2023":[{"f":"05\/09\/22","t":"V","p":"41"}]},"830":{"2022\/2023":[{"f":"05\/09\/22","t":"V","p":"4"}]},"841":{"2022\/2023":[{"f":"05\/09\/22","t":"V","p":"11"}]},"845":{"2022\/2023":[{"f":"05\/09\/22","t":"V","p":"41"}]},"846":{"2022\/2023":[{"f":"09\/03\/23","t":"S","p":"29"}]},"847":{"2022\/2023":[{"f":"05\/09\/22","t":"V","p":"41"}]},"849":{"2022\/2023":[{"f":"05\/09\/22","t":"V","p":"4"}]},"850":{"2022\/2023":[{"f":"05\/09\/22","t":"V","p":"4"}]},"854":{"2022\/2023":[{"f":"05\/09\/22","t":"V","p":"4"}]},"855":{"2022\/2023":[{"f":"05\/09\/22","t":"V","p":"41"}]},"862":{"2022\/2023":[{"f":"05\/09\/22","t":"V","p":"41"}]},"868":{"2022\/2023":[{"f":"05\/09\/22","t":"V","p":"21"}]},"872":{"2022\/2023":[{"f":"11\/04\/23","t":"S","p":"41"}]},"875":{"2022\/2023":[{"f":"05\/09\/22","t":"V","p":"41"}]},"877":{"2022\/2023":[{"f":"18\/10\/22","t":"S","p":"29"}]},"880":{"2022\/2023":[{"f":"05\/09\/22","t":"V","p":"41"}]},"881":{"2022\/2023":[{"f":"05\/09\/22","t":"V","p":"41"}]},"882":{"2022\/2023":[{"f":"05\/09\/22","t":"V","p":"41"}]},"891":{"2022\/2023":[{"f":"20\/09\/22","t":"S","p":"29"}]},"895":{"2022\/2023":[{"f":"05\/09\/22","t":"V","p":"21"}]},"897":{"2022\/2023":[{"f":"05\/09\/22","t":"V","p":"21"}]},"898":{"2022\/2023":[{"f":"05\/09\/22","t":"V","p":"41"}]},"899":{"2022\/2023":[{"f":"05\/09\/22","t":"V","p":"41"}]},"913":{"2022\/2023":[{"f":"05\/09\/22","t":"V","p":"11"}]},"915":{"2022\/2023":[{"f":"05\/09\/22","t":"V","p":"4"}]},"923":{"2022\/2023":[{"f":"05\/09\/22","t":"V","p":"4"}]},"929":{"2022\/2023":[{"f":"05\/09\/22","t":"V","p":"41"}]},"932":{"2022\/2023":[{"f":"05\/09\/22","t":"V","p":"41"},{"f":"25\/10\/22","t":"S","p":"41"}]},"933":{"2022\/2023":[{"f":"22\/09\/22","t":"S","p":"29"},{"f":"22\/11\/22","t":"S","p":"29"}]},"934":{"2022\/2023":[{"f":"10\/01\/23","t":"S","p":"29"}]},"942":{"2022\/2023":[{"f":"05\/09\/22","t":"V","p":"41"}]},"946":{"2022\/2023":[{"f":"05\/09\/22","t":"V","p":"41"}]},"949":{"2022\/2023":[{"f":"05\/09\/22","t":"V","p":"41"}]},"950":{"2022\/2023":[{"f":"05\/09\/22","t":"V","p":"41"}]},"956":{"2022\/2023":[{"f":"05\/09\/22","t":"V","p":"4"}]},"963":{"2022\/2023":[{"f":"05\/09\/22","t":"V","p":"4"}]},"965":{"2022\/2023":[{"f":"05\/09\/22","t":"V","p":"21"}]},"968":{"2022\/2023":[{"f":"05\/09\/22","t":"V","p":"41"}]},"969":{"2022\/2023":[{"f":"05\/09\/22","t":"V","p":"41"}]},"975":{"2022\/2023":[{"f":"05\/09\/22","t":"V","p":"41"}]},"976":{"2022\/2023":[{"f":"13\/09\/22","t":"V","p":"29"}]},"977":{"2022\/2023":[{"f":"05\/09\/22","t":"V","p":"41"}]},"982":{"2022\/2023":[{"f":"05\/09\/22","t":"V","p":"41"}]},"985":{"2022\/2023":[{"f":"05\/09\/22","t":"V","p":"41"}]},"988":{"2022\/2023":[{"f":"05\/09\/22","t":"V","p":"41"}]},"989":{"2022\/2023":[{"f":"05\/09\/22","t":"V","p":"41"}]},"994":{"2022\/2023":[{"f":"05\/09\/22","t":"V","p":"41"}]},"1002":{"2022\/2023":[{"f":"05\/09\/22","t":"V","p":"41"}]},"1012":{"2022\/2023":[{"f":"05\/09\/22","t":"V","p":"4"}]},"1014":{"2022\/2023":[{"f":"16\/02\/23","t":"S","p":"41"}]},"1026":{"2022\/2023":[{"f":"05\/09\/22","t":"V","p":"41"}]},"1082":{"2022\/2023":[{"f":"06\/06\/23","t":"S","p":"41"}]},"1107":{"2022\/2023":[{"f":"29\/11\/22","t":"S","p":"29"}]},"1129":{"2022\/2023":[{"f":"15\/09\/22","t":"V","p":"14"}]},"1158":{"2022\/2023":[{"f":"15\/09\/22","t":"V","p":"41"}]},"1177":{"2022\/2023":[{"f":"17\/01\/23","t":"S","p":"29"}]},"1193":{"2022\/2023":[{"f":"18\/04\/23","t":"S","p":"41"}]},"1202":{"2022\/2023":[{"f":"20\/09\/22","t":"S","p":"41"},{"f":"17\/11\/22","t":"S","p":"29"}]},"1210":{"2022\/2023":[{"f":"20\/09\/22","t":"S","p":"21"}]},"1266":{"2022\/2023":[{"f":"29\/09\/22","t":"S","p":"41"}]},"1284":{"2022\/2023":[{"f":"11\/10\/22","t":"S","p":"41"}]},"1294":{"2022\/2023":[{"f":"08\/11\/22","t":"S","p":"4"}]},"1298":{"2022\/2023":[{"f":"20\/10\/22","t":"S","p":"21"}]},"1303":{"2022\/2023":[{"f":"08\/11\/22","t":"S","p":"41"}]},"1306":{"2022\/2023":[{"f":"11\/10\/22","t":"S","p":"29"}]},"1327":{"2022\/2023":[{"f":"07\/02\/23","t":"S","p":"11"}]},"1328":{"2022\/2023":[{"f":"02\/05\/23","t":"S","p":"29"}]},"1334":{"2022\/2023":[{"f":"20\/10\/22","t":"S","p":"29"}]},"1356":{"2022\/2023":[{"f":"20\/10\/22","t":"S","p":"23"},{"f":"03\/11\/22","t":"S","p":"14"}]},"1357":{"2022\/2023":[{"f":"20\/10\/22","t":"S","p":"11"}]},"1368":{"2022\/2023":[{"f":"08\/11\/22","t":"S","p":"41"}]},"1375":{"2022\/2023":[{"f":"18\/04\/23","t":"S","p":"41"}]},"1401":{"2022\/2023":[{"f":"10\/11\/22","t":"S","p":"11"}]},"1429":{"2022\/2023":[{"f":"17\/11\/22","t":"S","p":"29"}]},"1465":{"2022\/2023":[{"f":"09\/03\/23","t":"S","p":"11"}]},"1488":{"2022\/2023":[{"f":"17\/03\/23","t":"S","p":"29"}]},"1499":{"2022\/2023":[{"f":"20\/04\/23","t":"S","p":"29"}]},"1500":{"2022\/2023":[{"f":"09\/06\/23","t":"S","p":"29"}]},"1513":{"2022\/2023":[{"f":"11\/05\/23","t":"S","p":"4"}]},"1515":{"2022\/2023":[{"f":"14\/02\/23","t":"S","p":"21"}]},"1523":{"2022\/2023":[{"f":"23\/05\/23","t":"S","p":"41"}]},"1536":{"2022\/2023":[{"f":"23\/05\/23","t":"S","p":"29"}]},"1557":{"2022\/2023":[{"f":"30\/05\/23","t":"S","p":"11"}]}}}